lyricsgenius/__init__.py
lyricsgenius/__main__.py
lyricsgenius/auth.py
lyricsgenius/errors.py
lyricsgenius/genius.py
lyricsgenius/utils.py
lyricsgenius/api/__init__.py
lyricsgenius/api/api.py
lyricsgenius/api/base.py
lyricsgenius/api/protocols.py
lyricsgenius/api/public_methods/__init__.py
lyricsgenius/api/public_methods/album.py
lyricsgenius/api/public_methods/annotation.py
lyricsgenius/api/public_methods/article.py
lyricsgenius/api/public_methods/artist.py
lyricsgenius/api/public_methods/cover_art.py
lyricsgenius/api/public_methods/discussion.py
lyricsgenius/api/public_methods/leaderboard.py
lyricsgenius/api/public_methods/misc.py
lyricsgenius/api/public_methods/question.py
lyricsgenius/api/public_methods/referent.py
lyricsgenius/api/public_methods/search.py
lyricsgenius/api/public_methods/song.py
lyricsgenius/api/public_methods/user.py
lyricsgenius/api/public_methods/video.py
lyricsgenius/types/__init__.py
lyricsgenius/types/album.py
lyricsgenius/types/artist.py
lyricsgenius/types/base.py
lyricsgenius/types/song.py
lyricsgenius/types/types.py
lyricsgenius-3.7.1.dist-info/METADATA
lyricsgenius-3.7.1.dist-info/WHEEL
lyricsgenius-3.7.1.dist-info/licenses/LICENSE.txt
lyricsgenius-3.7.1.dist-info/RECORD
