Metadata-Version: 2.4
Name: lyricsgenius
Version: 3.7.1
Summary: Download lyrics and metadata from Genius.com
Project-URL: Homepage, https://www.johnwmillr.com/scraping-genius-lyrics/
Project-URL: Documentation, https://lyricsgenius.readthedocs.io/en/master/
Project-URL: Repository, https://github.com/johnwmillr/LyricsGenius
Project-URL: Issues, https://github.com/johnwmillr/LyricsGenius/issues
Author-email: "John W. R. Miller" <john.w.millr+lg@gmail.com>
License-Expression: MIT
License-File: LICENSE.txt
Keywords: download-lyrics,download-song-lyrics,genius,genius-api,genius-lyrics,lyrics,lyricsgenius,scraping-lyrics,song-lyrics
Requires-Python: >=3.10
Requires-Dist: beautifulsoup4>=4.12.3
Requires-Dist: requests>=2.27.1
Provides-Extra: checks
Requires-Dist: doc8>=0.11.2; extra == 'checks'
Requires-Dist: flake8-bugbear>=22.9.23; extra == 'checks'
Requires-Dist: flake8>=4.0.1; extra == 'checks'
Requires-Dist: pygments>=2.14.0; extra == 'checks'
Requires-Dist: tox>=3.28.0; extra == 'checks'
Provides-Extra: docs
Requires-Dist: sphinx-rtd-theme>=1.3.0; extra == 'docs'
Requires-Dist: sphinx>=4.3.2; extra == 'docs'
